drawstuffpy/__init__.py
drawstuffpy/drawstuff.py
drawstuffpy/version.py
odepy/__init__.py
odepy/collision.py
odepy/collision_space.py
odepy/collision_trimesh.py
odepy/common.py
odepy/contact.py
odepy/error.py
odepy/mass.py
odepy/matrix.py
odepy/memory.py
odepy/misc.py
odepy/objects.py
odepy/odeinit.py
odepy/odemath.py
odepy/rotation.py
odepy/threading.py
odepy/threading_impl.py
odepy/timer.py
test/__init__.py
test/conftest.py
test/test_joint.py
test/test_joint2.py
test/test_space.py
test/test_world.py
test/utils/__init__.py
test/utils/drawstuff.py
test/utils/nearcallback.py
test/utils/space.py
test/utils/world.py
ode_python-0.0.9.dist-info/LICENSE
ode_python-0.0.9.dist-info/METADATA
ode_python-0.0.9.dist-info/WHEEL
ode_python-0.0.9.dist-info/top_level.txt
ode_python-0.0.9.dist-info/RECORD
