Metadata-Version: 2.1
Name: ode-python
Version: 0.0.9
Summary: Open Dynamics Engine (ODE) python binding.
Home-page: https://github.com/qoosky/ode-python
Author: Qoosky
Author-email: qoosky.webshop@gmail.com
License: MIT
Platform: UNKNOWN
Classifier: Programming Language :: Python :: 2
Classifier: Programming Language :: Python :: 3
Classifier: License :: OSI Approved :: MIT License
Classifier: Operating System :: POSIX :: Linux
